eagle/tools/__init__.py
eagle/tools/amlsync.py
eagle/tools/cli.py
eagle/tools/data.py
eagle/tools/inference.py
eagle/tools/log.py
eagle/tools/metrics.py
eagle/tools/nested.py
eagle/tools/postprocess.py
eagle/tools/postwxvx.py
eagle/tools/prewxvx.py
eagle/tools/reshape.py
eagle/tools/spatial.py
eagle/tools/spectra.py
eagle/tools/utils.py
eagle/tools/visualize.py
eagle/tools/config/__init__.py
eagle/tools/config/defaults.yaml
eagle/tools/config/met.yaml
eagle/tools/config/rename.yaml
eagle_tools-0.6.3.dist-info/licenses/LICENSE
eagle_tools-0.6.3.dist-info/METADATA
eagle_tools-0.6.3.dist-info/WHEEL
eagle_tools-0.6.3.dist-info/entry_points.txt
eagle_tools-0.6.3.dist-info/top_level.txt
eagle_tools-0.6.3.dist-info/RECORD
