Metadata-Version: 2.4
Name: eagle-tools
Version: 0.6.3
Summary: Tools for processing and evaluating anemoi based EAGLE ML models.
Author-email: Timothy Smith <tim.smith@noaa.gov>
Classifier: Programming Language :: Python :: 3
Classifier: License :: OSI Approved :: MIT License
Classifier: Operating System :: OS Independent
Requires-Python: >=3.10
License-File: LICENSE
Requires-Dist: click
Requires-Dist: numpy
Requires-Dist: scipy
Requires-Dist: pandas
Requires-Dist: xarray
Requires-Dist: zarr<3
Requires-Dist: ufs2arco>=0.17.2
Requires-Dist: anemoi-datasets
Requires-Dist: anemoi-inference
Requires-Dist: matplotlib
Requires-Dist: cartopy
Requires-Dist: cmocean
Dynamic: license-file
